LICENSE
MANIFEST.in
README.rst
setup.cfg
setup.py
tox.ini
demo/metadata/get/allow/.headers
demo/metadata/get/allow/record.json
demo/metadata/get/forbidden/.status
demo/metadata/get/forbidden/record.json
demo/production/production_conf.py
demo/production/production_conf.pyc
demo/production/production_server.py
demo/production/__pycache__/production_conf.cpython-33.pyc
demo/production/get/available/1.json
demo/production/get/available/3.json
demo/simple/get/sounds.json
demo/simple/get/members/100.json
demo/simple/get/members/200.json
demo/simple/get/members/300.json
demo/simple/get/members/400.json
demo/simple/get/members/500.json
demo/simple/get/members/600.json
demo/simple/get/members/700.json
demo/simple/get/members/800.json
demo/simple/get/members/900.json
demo/simple/post/members.json
demo/simple/static/index.html
demo/simple/static/script.js
hunk/__init__.py
hunk/_compat.py
hunk/production.py
hunk/resource.py
hunk/server.py
hunk.egg-info/PKG-INFO
hunk.egg-info/SOURCES.txt
hunk.egg-info/dependency_links.txt
hunk.egg-info/entry_points.txt
hunk.egg-info/not-zip-safe
hunk.egg-info/requires.txt
hunk.egg-info/top_level.txt
tests/__init__.py
tests/_compat.py
tests/test_demo.py