Metadata-Version: 1.1
Name: hunk
Version: 0.1.0
Summary: Mock for JSON API server.
Home-page: https://github.com/lanius/hunk/
Author: lanius
Author-email: lanius@nirvake.org
License: Copyright (C) 2014 by lanius
